AUTHORS
LICENSE
MANIFEST.in
README.rst
setup.py
dbsettings/__init__.py
dbsettings/forms.py
dbsettings/group.py
dbsettings/loading.py
dbsettings/management.py
dbsettings/models.py
dbsettings/settings.py
dbsettings/signals.py
dbsettings/urls.py
dbsettings/utils.py
dbsettings/values.py
dbsettings/views.py
dbsettings/locale/pl/LC_MESSAGES/django.mo
dbsettings/locale/pl/LC_MESSAGES/django.po
dbsettings/migrations/0001_initial.py
dbsettings/migrations/__init__.py
dbsettings/templates/dbsettings/app_settings.html
dbsettings/templates/dbsettings/image_widget.html
dbsettings/templates/dbsettings/site_settings.html
dbsettings/templates/dbsettings/values.html
django_dbsettings.egg-info/PKG-INFO
django_dbsettings.egg-info/SOURCES.txt
django_dbsettings.egg-info/dependency_links.txt
django_dbsettings.egg-info/not-zip-safe
django_dbsettings.egg-info/top_level.txt