Metadata-Version: 1.2
Name: django-dbsettings
Version: 1.2.0
Summary: Application settings whose values can be updated while a project is up and running.
Home-page: http://github.com/zlorf/django-dbsettings
Author: Samuel Cormier-Iijima
Author-email: sciyoshi@gmail.com
Maintainer: Jacek Tomaszewski
Maintainer-email: jacek.tomek@gmail.com
License: BSD
Platform: UNKNOWN
Classifier: Development Status :: 4 - Beta
Classifier: Environment :: Web Environment
Classifier: Framework :: Django
Classifier: Intended Audience :: Developers
Classifier: License :: OSI Approved :: BSD License
Classifier: Operating System :: OS Independent
Classifier: Programming Language :: Python :: 3
Classifier: Topic :: Utilities
